ifc4d/__init__.py
ifc4d/common.py
ifc4d/csv2ifc.py
ifc4d/csv4d2ifc.py
ifc4d/ifc2msp.py
ifc4d/ifc2p6.py
ifc4d/msp2ifc.py
ifc4d/p62ifc.py
ifc4d/p6xer2ifc.py
ifc4d/pp2ifc.py
ifc4d/test.py
ifc4d/wpattern.py
ifc4d-0.8.3.dist-info/METADATA
ifc4d-0.8.3.dist-info/WHEEL
ifc4d-0.8.3.dist-info/top_level.txt
ifc4d-0.8.3.dist-info/RECORD
